[{"model": "Basic_Query.teacher", "pk": "0ee12cfa-44f1-4121-bc56-d669ebb49246", "fields": {"name": "Ishak", "emplyee_id": "t-1001", "city": "Khulna", "salary": 56747, "joiningDate": "2011-11-23T00:09:00Z"}}, {"model": "Basic_Query.teacher", "pk": "1323d372-cf10-4281-b2c0-fc4e4c072e81", "fields": {"name": "Dr. Tarek Habbib", "emplyee_id": "t-1007", "city": "Rajshahi", "salary": 124335, "joiningDate": "2022-12-28T22:02:00Z"}}, {"model": "Basic_Query.teacher", "pk": "48f6172c-d0f4-408a-84bb-81adf3ae9438", "fields": {"name": "Md Nazmul Alam", "emplyee_id": "t-1003", "city": "Cumilla", "salary": 80345, "joiningDate": "2023-03-05T17:36:00Z"}}, {"model": "Basic_Query.teacher", "pk": "69872354-6a2c-450b-a234-ad52a03c3ea4", "fields": {"name": "Dr. Sadikur Rahman", "emplyee_id": "t-1006", "city": "Rangpur", "salary": 138884, "joiningDate": "2022-12-25T07:58:00Z"}}, {"model": "Basic_Query.teacher", "pk": "6afdd0e2-df7e-42fc-a256-dfc0567b3607", "fields": {"name": "Dr. Mohammad Zabiullah", "emplyee_id": "t-1008", "city": "Cumilla", "salary": 432000, "joiningDate": "2023-01-11T17:30:00Z"}}, {"model": "Basic_Query.teacher", "pk": "c228f792-6822-4f30-a6eb-a4b51a111f5c", "fields": {"name": "Md Abir", "emplyee_id": "t-1002", "city": "Barisal", "salary": 23556, "joiningDate": "2014-09-13T04:27:00Z"}}, {"model": "Basic_Query.teacher", "pk": "c477167a-2a85-43d2-95d1-21432c7b060f", "fields": {"name": "Anower khan", "emplyee_id": "t-1005", "city": "Barisal", "salary": 75467, "joiningDate": "2007-07-22T00:37:00Z"}}, {"model": "Basic_Query.teacher", "pk": "de2ae46e-a248-476e-92cc-aab4d6bd225e", "fields": {"name": "Kobir Hossin", "emplyee_id": "t-1004", "city": "Mymensingh", "salary": 120000, "joiningDate": "2007-08-14T07:42:00Z"}}]